shmdash/__init__.py
shmdash/_client.py
shmdash/_datatypes.py
shmdash/_exceptions.py
shmdash/_http.py
shmdash/_utils.py
shmdash-0.6.0.dist-info/METADATA
shmdash-0.6.0.dist-info/WHEEL
shmdash-0.6.0.dist-info/licenses/LICENSE.txt
shmdash-0.6.0.dist-info/RECORD
