Metadata-Version: 2.3
Name: shmdash
Version: 0.6.0
Summary: Vallen Systeme Dashboard (SHM Dash) upload client
Project-URL: Source, https://github.com/vallen-systems/pySHMdash
Project-URL: Issues, https://github.com/vallen-systems/pySHMdash/issues
Author-email: "Lukas Berbuer (Vallen Systeme GmbH)" <lukas.berbuer@vallen.de>
License: MIT License
License-File: LICENSE.txt
Keywords: client,dashboard,shmdash,upload,vallen
Classifier: Development Status :: 4 - Beta
Classifier: Intended Audience :: Developers
Classifier: License :: OSI Approved :: MIT License
Classifier: Operating System :: OS Independent
Classifier: Programming Language :: Python :: 3
Classifier: Programming Language :: Python :: 3 :: Only
Classifier: Programming Language :: Python :: 3.7
Classifier: Programming Language :: Python :: 3.8
Classifier: Programming Language :: Python :: 3.9
Classifier: Programming Language :: Python :: 3.10
Classifier: Programming Language :: Python :: 3.11
Classifier: Programming Language :: Python :: 3.12
Requires-Python: >=3.7
Requires-Dist: httpx>=0.27
Provides-Extra: dev
Requires-Dist: coverage[toml]>=5; extra == 'dev'
Requires-Dist: hatch; extra == 'dev'
Requires-Dist: mypy>=0.9; extra == 'dev'
Requires-Dist: pytest-asyncio; extra == 'dev'
Requires-Dist: pytest>=6; extra == 'dev'
Requires-Dist: ruff>=0.5; extra == 'dev'
Provides-Extra: tests
Requires-Dist: coverage[toml]>=5; extra == 'tests'
Requires-Dist: pytest-asyncio; extra == 'tests'
Requires-Dist: pytest>=6; extra == 'tests'
Provides-Extra: tools
Requires-Dist: hatch; extra == 'tools'
Requires-Dist: mypy>=0.9; extra == 'tools'
Requires-Dist: ruff>=0.5; extra == 'tools'
